paras_lib/__init__.py
paras_lib/functions.py
paras_lib-0.12.dist-info/METADATA
paras_lib-0.12.dist-info/WHEEL
paras_lib-0.12.dist-info/top_level.txt
paras_lib-0.12.dist-info/RECORD
