Metadata-Version: 2.1
Name: paras-lib
Version: 0.12
Summary: A custom functions package for common operations
Home-page: https://github.com/embivert/paras_lib
Author: Paras Singh
Author-email: paras.singh@shl.com
Classifier: Programming Language :: Python :: 3
Classifier: License :: OSI Approved :: MIT License
Classifier: Operating System :: OS Independent
Requires-Python: >=3.6
